dorcas_sdk_python/__init__.py
dorcas_sdk_python/helpers.py
dorcas_sdk_python/resources.py
dorcas_sdk_python/services.py
example/__init__.py
example/sdk_sample.py
tests/__init__.py
tests/test_payload.py
tests/test_resources.py
tests/test_response.py
tests/test_sdk.py
tests/test_services.py
dorcas_sdk_python-0.0.1.dist-info/LICENSE
dorcas_sdk_python-0.0.1.dist-info/METADATA
dorcas_sdk_python-0.0.1.dist-info/WHEEL
dorcas_sdk_python-0.0.1.dist-info/top_level.txt
dorcas_sdk_python-0.0.1.dist-info/RECORD
