Metadata-Version: 2.1
Name: dorcas-sdk-python
Version: 0.0.1
Summary: A Python wrapper for communicating with the Dorcas API
Home-page: https://gitlab.com/dorcasng/dorcas-sdk-python
Author: Emmanuel Okeke
Author-email: emmanix2002@gmail.com
License: UNKNOWN
Platform: UNKNOWN
Classifier: Programming Language :: Python :: 3
Classifier: License :: OSI Approved :: MIT License
Classifier: Operating System :: OS Independent
